safety_checker-0.5.dist-info/METADATA
safety_checker-0.5.dist-info/WHEEL
safety_checker-0.5.dist-info/licenses/LICENSE
safety_checker/__init__.py
safety_checker/sdhook.py
safety_checker-0.5.dist-info/RECORD
