Metadata-Version: 2.1
Name: safety-checker
Version: 0.5
Summary: Integrate stable diffusion safety checker / NSFW image detection into web service like FastAPI.
Author-Email: iyume <iyumelive@gmail.com>
License: Apache-2.0
Requires-Python: >=3.8
Requires-Dist: Pillow>=8.4.0
Requires-Dist: transformers>=4.0; extra == "sdhook"
Requires-Dist: diffusers[torch]>=0.20; extra == "sdhook"
Provides-Extra: sdhook
